{
  "cover": "https://image.aladin.co.kr/product/32782/19/cover500/k032936488_1.jpg",
  "title": "호박 목욕탕",
  "author": "시바타 게이코 (지은이), 황진희 (옮긴이)",
  "publisher": "위즈덤하우스",
  "year": 2023,
  "description": "꽁꽁 언 추위를 즐거운 유머로 녹이는 유쾌한 이야기 《호박 목욕탕》은 일본 통산 180만 부 베스트셀러 &lt;빵도둑&gt; 시리즈의 작가 시바타 케이코의 그림책이다. 하지 말라는 일을 저지른 새하얀 세 동물에게 앞으로 무슨 일이 일어날까?",
  "categoryName": "국내도서>유아>그림책>나라별 그림책>일본",
  "itemPage": 40,
  "ratingScore": 0,
  "priceStandard": 16700,
  "link": "https://www.aladin.co.kr/shop/wproduct.aspx?ItemId=327821999&amp;partner=openAPI&amp;start=api"
}