{
  "cover": "https://image.aladin.co.kr/product/31752/0/cover500/k062833000_1.jpg",
  "title": "변비 탐정 실룩 1 : 사과 도둑을 찾아라!",
  "author": "이나영 (지은이), 박소연 (그림)",
  "publisher": "북스그라운드",
  "year": 2023,
  "description": "《시간 가게》로 문학동네어린이문학상을 수상한 이나영 작가의 작품이다. 변비 걸린 붉은 토끼 ‘실룩’이 수다쟁이 참새 조수 ‘소소’와 함께 셜록 뺨치는 추리력으로 의뢰받은 사건을 막힘없이 해결하는 과정이 흥미진진하게 펼쳐진다.",
  "categoryName": "국내도서>어린이>동화/명작/고전>국내창작동화",
  "itemPage": 104,
  "ratingScore": 0,
  "priceStandard": 13000,
  "link": "https://www.aladin.co.kr/shop/wproduct.aspx?ItemId=317520007&amp;partner=openAPI&amp;start=api"
}